{
    "nav1Txt": "Inicio",
    "nav2Txt": "Sobre mi",
    "nav3Txt": "Educación",
    "nav4Txt": "Skills",
    "nav5Txt": "Proyectos",
    "inicioPhTxt": "Desarrollador Frontend",
    "DwnCVTxt": "Descargar CV",
    "sobreMi1Txt": "Sobre mi",
    "sobreMi2Txt": "Hola!!, soy desarrollador web frontend con experiencia en crear interfaces dinámicas y responsivas. Mi portfolio es un reflejo de mi compromiso con la excelencia en diseño y usabilidad, destacando proyectos que combinan funcionalidad y estética.",
    
    "aptitudes1Txt": "Experiencia y Educación",
    "aptitudesh21Txt": "Experiencia",
    "aptitudesh22Txt": "Educación",
    "aptitudes2Txt": "Grado medio SMR",
    "aptitudes3Txt": "Grado superior DAW",
    "aptitudes4Txt": "Ayesa",
    "aptitudes5Txt": "Becario",
    "aptitudes6Txt": "En las prácticas en el grado superior de DAW en Ayesa mi trabajo fue la resolución de incidencias de su cliente, dichas incidencias consistían en sentencias SQL y depurar distintas aplicaciones en JavaScript y .Net para encontrar fallos que el cliente indica",
    
    "proyectos1Txt": "Proyectos"
}